{
    "personal_information": {
        "full_name": "",
        "date_of_birth": "",
        "age": "",
        "gender": "",
        "email": "",
        "phone": "",
        "address": "",
        "LinkedIn": null,
        "Instagram": null,
        "Twitter": null,
        "website": null
    },
    "languages": [],
    "education": [],
    "work_experience": [],
    "hard_and_soft_skills": {
        "hard_skills": [],
        "soft_skills": []
    },
    "other_interests": [],
    "volunteering": [],
    "raw_text": "personal information work experience jul 2019dec 2020 feb 2019jul 2019 2017present sep 2015-jun 2017 education and training 2016-2019 18 feb 2019-12 jun 2019 marcos casado q bomi 15, 28691 villanueva de la caada (spain) @ +346967351 19 ja marcoscasado6(mhotmail.com fi] httos:/avww.linkedin.com/in/marcoscasado6/ date of birth 02/05/1994 nationality spanish oooo y systems and software engineering ct ingenieros airbus a400m mids (multifunctional information distribution system), c2 (command and control) system over link-16 - validation and verification (v&v) electronic warfare systems integration - airbus xplorers (ax), internship + bsc thesis airbus defence and space prototyping an electronic warfare defensive computer and cockpit display unit that integrates a missile warning system (mws), countermeasures dispensing system (cmds) and radar warning system (rws), in order to increase the situational awareness, avoid threats and find best dispensing solution to be executed. - model-based development for safety-critical and mission-critical embedded control applications with scade suite. co-founder and full-stack developer networkcode tech solutions sl entrepreneur project based mainly on web application development and business digitalization. educational robotics professor ria - robots in action, madrid (spain) en a bsc in telecommunication engineering, telematics carlos iii madrid university, madrid (spain) seedbed, program in business skills escuela de organización industrial business and soft skills . * seedbed is a program created by airbus to compliment the academic curricula of the engineering students of airbus key universities. [...] page 1/2 2017-2018 personal skills mother tongue(s) foreign language(s) english additional information honours and awards certifications certifications certifications seminars about me additional information marcos casado erasmus program in finland university of vaasa and vamk (university of applied sciences), vaasa (finland) ooo spanish understanding speaking writing listening c1 c1 c1 c1 c1 levels: a1 and a2: basic user - b1 and b2: independent user - c1 and c2: proficient user common european framework of reference for languages reading spoken interaction spoken production ee y champions of the hackathon organized by ibm, university carlos lll of madrid and best (board of european students of technology) 2016 cs50's web programming with python and javascript. by harvardx - an online learning initiative by harvard university through edx htmls5, css, javascript, android and ios development introduction course (6 ed) by upm - polytechnic university of madrid connecting the future with optical fiber. introduction course about the optical fiber and how it is deployed. by telefonica digital education. google hashcode 2016 participant. as a short introduction of me, i'm a person who like sports, technology (electronics, automotive, aeronautics, ...) and spend time with friends. people describe me as an autodidact and hard worker person with the skills to deal with problems and solve them. i'm always willing to learn new things and to come up with ideas. more than two years as padel coach in up center indoor and second division player of the fmp (\"federación madrilea de padel\") page 2 / 2",
    "text_from_header": "PERSONAL INFORMATION",
    "detected_language": "en",
    "master_edition": "MASI20"
}