{
    "personal_information": {
        "full_name": "",
        "date_of_birth": "",
        "age": "",
        "gender": "",
        "email": "",
        "phone": "",
        "address": "",
        "LinkedIn": null,
        "Instagram": null,
        "Twitter": null,
        "website": null
    },
    "languages": [],
    "education": [],
    "work_experience": [],
    "hard_and_soft_skills": {
        "hard_skills": [],
        "soft_skills": []
    },
    "other_interests": [],
    "volunteering": [],
    "raw_text": "david barragán gómez 662 669 026 linkedin.com/in/david-barragan-gomez davidbarragangomez@qmail.com titulacion grado en ingenieria mecanica. sept. 2016 - feb. 2022 universidad de castilla-la mancha ciudad real. experiencia profesional estudiante colaborador (trabajo fin de grado). feb. 2021 - jun. 2021 centro nacional del hidrógeno (cnh2) puertollano, ciudad real. + analisis de porosidad en ánodos de pilas de combustible sofc mediante impresión 3d. + diseo de canales de alimentación en interconectores de celdas de combustible sofc. + fabricación de interconectores para stacks de celdas sofc mediante moldeo por inyección de polvos. + prototipado de una monocelda sofc testeada durante más de 200 horas. prácticas de ingeniería mecánica. jun. 2020 - ago. 2020 fertiberia puertollano, ciudad real. + diseo de piezas y ensamblajes en cad 3d con solidworks. - estudios de pérdidas económicas en materia de coste-oportunidad de equipo defectuoso. habilidades e idiomas habilidades: solidworks (avanzado) cype (intermedio) paquete office (intermedio) impresión 3d pim idiomas: inglés (fluido). cambridge english advanced (cae-c1). premios y reconocimientos premio cogiti (colegio oficial de graduados e ingenieros y técnicos industriales) al mejor trabajo fin de grado 2022 \"hacía el escalado industrial en la fabricación de pilas sofc mediante impresión 3d y mim. formación complementaria curso en análisis de riesgos industriales en plantas químicas y petroleras (haz-op). feb. 2020 impartido por el grupo imaes y repsol puertollano (204 edición). voluntariado proyecto smile (animación de hospital). asociación espaola contra el cáncer (aecc). protectora de animales y plantas huellas puertollano.",
    "text_from_header": null,
    "detected_language": "es",
    "master_edition": "MASI22"
}