{
    "personal_information": {
        "full_name": "",
        "date_of_birth": "",
        "age": "",
        "gender": "",
        "email": "",
        "phone": "",
        "address": "",
        "LinkedIn": null,
        "Instagram": null,
        "Twitter": null,
        "website": null
    },
    "languages": [],
    "education": [],
    "work_experience": [],
    "hard_and_soft_skills": {
        "hard_skills": [],
        "soft_skills": []
    },
    "other_interests": [],
    "volunteering": [],
    "raw_text": "paloma álvarez yáez ingeniera industrial información de contacto +34 647822852 palomalvarezl5ggmail.com donostia-san sebastián, guipúzcoa, espaa. www.linkedin.com/in/palomaalv arezyanez aptitudes y habilidades - persona con gran motivacion y disciplina. - trabajadora en equipo. - abierta a nuevas experiencias formativas y profesionales. reconocimientos finalista del edpr university challenge 2021 con el proyecto \"caracterización del comportamiento mecánico de aceros con objeto de asegurar un diseo seguro de componentes para prestar servicios bajo alta presión de hidrógeno\". 2021 - actualmente estudiante del máster en ingeniería industrial en tecnun - universidad de navarra. experiencia profesional construcciones metálicas muiz hermanos sl. la huelga, s/n. 33469 tamón (carreo). prácticas de la universidad de oviedo. febrero 2021. participación en todos los departamentos de la empresa, entre lo que se incluye la valoración de ofertas y la participación en los procesos industriales desarrollados. educación 2016-2021 grado en ingeniería en tecnologías industriales en la universidad de oviedo. 2016 a 2018 en la universidad de oviedo. 2018 a 2019 erasmus en la akademia górniczo- hutnicza: university of science and tecnology, cracovia (polonia). 2019 a 2021 en la universidad de oviedo. nota media: 7.486 cursos y formaciones e programa tecnun-lese. iese (madrid) octubre 2021. conocimientos informáticos e matlab. e autocad. e autodesk inventor. e creo. e paquete microsoftoffice. idiomas e espaol (lengua materna). e inglés b2 first certificate. otros e carnet de conducir.",
    "text_from_header": "INGENIERA INDUSTRIAL",
    "detected_language": "es",
    "master_edition": "MASI22"
}