{
    "personal_information": {
        "full_name": "",
        "date_of_birth": "",
        "age": "",
        "gender": "",
        "email": "",
        "phone": "",
        "address": "",
        "LinkedIn": null,
        "Instagram": null,
        "Twitter": null,
        "website": null
    },
    "languages": [],
    "education": [],
    "work_experience": [],
    "hard_and_soft_skills": {
        "hard_skills": [],
        "soft_skills": []
    },
    "other_interests": [],
    "volunteering": [],
    "raw_text": "estacio moya, alejandro datos personales dirección: c/ virgen del mar, 25, 7b. 28821. coslada - madrid fecha de nacimiento: 23 noviembre 1.982 teléfonos de contacto: 627.90.91.67 / 91.674.06.53 correo electrónico: alejandro.estacio@gmail.com permiso de conducir: tipo b formacion academica 2009: aeronautical engineering (avionics) glyndwr university. wrexham. walles. united kingdom. 2009: ingeniero técnico de telecomunicaciones en sistemas electrónicos universidad politécnica alcala de henares uah (madrid). 2002: técnico superior en desarrollo de productos electrónicos. centro superior de formación padre piquer (madrid). formación adicional, o prevención de riesgos laborales nivel 1 (60 horas). universidad alcalá de henares uah (madrid). ofimática (80 horas). mecanografía (50 horas). inglés para ingenieros (90 horas). centro superior de formación padre piquer (madrid). título de inglés nivel pre-intermediate del british council. 2009. glyndwr university. walles. united kingdom. oooo experiencia laboral a octubre 2006 - mayo 2007: vodafone back-up / coordinador de la plataforma en san sebastián de los reyes (madrid). administré, supervisé y controlé gestiones de un call-center, así como de la plantilla. o febrero 2005 - octubre 2006: vodafone teleoperador en atención al cliente y empresas. q abril 2002 - agosto 2002: beep (grupo de servicios informáticos) técnico en el servicio de asistencia técnica y venta de suministros en tienda. idiomas o espaol: lengua materna. q inglés: nivel alto (hablado, escrito y conversación). herramientas informaticas q software general: internet, correo electrónico, windows (9x, nt, me, 2000, xp, vista), linux, microsoft office. q programación en c, c++, pascal, vhdl, visual basic, matlab, proview32, flashmagic, ensamblador. q programas de diseo y simulación de circuitos electrónicos: orcad, tango, workbench. otros datos a abril 2006 - participación en campeonato nacional de robótica hispabot. facultad politécnica. universidad alcalá de henares uah (madrid).",
    "text_from_header": "ESTACIO MOYA, ALEJANDRO",
    "detected_language": "es",
    "master_edition": "MASI10"
}